vl6180x_multi/__init__.py
vl6180x_multi/vl6180x_multi.py
vl6180x_multi-1.0.2.dist-info/LICENSE
vl6180x_multi-1.0.2.dist-info/METADATA
vl6180x_multi-1.0.2.dist-info/WHEEL
vl6180x_multi-1.0.2.dist-info/top_level.txt
vl6180x_multi-1.0.2.dist-info/RECORD
