Metadata-Version: 2.1
Name: vl6180x-multi
Version: 1.0.2
Summary: Multiple VL6180X time of flight distance sensors on the same I2C bus.
Home-page: https://gitlab.com/vitus133/vl6180x_multi
Author: Vitaly Grinberg
Author-email: vtalikgr@gmail.com
License: UNKNOWN
Platform: UNKNOWN
Classifier: Programming Language :: Python :: 3
Classifier: License :: OSI Approved :: MIT License
Classifier: Operating System :: OS Independent
Requires-Python: >=3.6
Requires-Dist: Adafruit-Blinka
Requires-Dist: adafruit-circuitpython-busdevice
Requires-Dist: adafruit-circuitpython-lis3dh
Requires-Dist: adafruit-circuitpython-vl6180x
Requires-Dist: Adafruit-PlatformDetect
Requires-Dist: Adafruit-PureIO
Requires-Dist: pigpio
Requires-Dist: pkg-resources
Requires-Dist: pyftdi
Requires-Dist: pyusb
Requires-Dist: rpi-ws281x
Requires-Dist: RPi.GPIO
Requires-Dist: sysv-ipc
